verilog/day06_counter_and _registers/counter_down.v
module counter_down(
	input clk,
	input rst,
	output reg [3:0] count
);
always @(posedge clk or posedge rst) begin
	if (rst)
		count <= 4'b0000;
	else
		count <= count - 1;
end 
endmodule

verilog/day06_counter_and _registers/counter_down_tb.v
module counter_down_tb;
  reg clk, rst;
  wire [3:0] count;

  counter_down uut (.clk(clk), .rst(rst), .count(count));

  initial begin
    $dumpfile("counter_down.vcd");
    $dumpvars(0, counter_down_tb);
    clk = 0; forever #5 clk = ~clk;
  end

  initial begin
    rst = 1; #10;
    rst = 0; #80;
    $finish;
  end
endmodule

verilog/day06_counter_and _registers/counter_down.vcd
$date
	Fri May 30 20:15:04 2025
$end
$version
	Icarus Verilog
$end
$timescale
	1s
$end
$scope module counter_down_tb $end
$var wire 4 ! count [3:0] $end
$var reg 1 " clk $end
$var reg 1 # rst $end
$scope module uut $end
$var wire 1 " clk $end
$var wire 1 # rst $end
$var reg 4 $ count [3:0] $end
$upscope $end
$upscope $end
$enddefinitions $end
$comment Show the parameter values. $end
$dumpall
$end
#0
$dumpvars
b0 $
1#
0"
b0 !
$end
#5
1"
#10
0"
0#
#15
b1111 !
b1111 $
1"
#20
0"
#25
b1110 !
b1110 $
1"
#30
0"
#35
b1101 !
b1101 $
1"
#40
0"
#45
b1100 !
b1100 $
1"
#50
0"
#55
b1011 !
b1011 $
1"
#60
0"
#65
b1010 !
b1010 $
1"
#70
0"
#75
b1001 !
b1001 $
1"
#80
0"
#85
b1000 !
b1000 $
1"
