verilog/day06_counter_and _registers/piso.v
module piso (
  input clk,
  input rst,
  input load,
  input [3:0] data_in,
  output reg dout
);
  reg [3:0] temp;

  always @(posedge clk or posedge rst) begin
    if (rst)
      temp <= 0;
    else if (load)
      temp <= data_in;
    else
      temp <= {temp[2:0], 1'b0};
  end

  always @(posedge clk or posedge rst)
    if (rst)
      dout <= 0;
    else
      dout <= temp[3];  // MSB goes out first
endmodule

verilog/day06_counter_and _registers/piso_tb.v
module piso_tb;
  reg clk, rst, load;
  reg [3:0] data_in;
  wire dout;

  piso uut (.clk(clk), .rst(rst), .load(load), .data_in(data_in), .dout(dout));

  initial begin
    $dumpfile("piso.vcd");
    $dumpvars(0, piso_tb);
    clk = 0;
    forever #5 clk = ~clk;
  end

  initial begin
    rst = 1; #10;
    rst = 0;
    data_in = 4'b1101; load = 1; #10;
    load = 0; #40;
    $finish;
  end
endmodule

verilog/day06_counter_and _registers/piso.vcd
$date
	Fri May 30 20:15:04 2025
$end
$version
	Icarus Verilog
$end
$timescale
	1s
$end
$scope module piso_tb $end
$var wire 1 ! dout $end
$var reg 1 " clk $end
$var reg 4 # data_in [3:0] $end
$var reg 1 $ load $end
$var reg 1 % rst $end
$scope module uut $end
$var wire 1 " clk $end
$var wire 4 & data_in [3:0] $end
$var wire 1 $ load $end
$var wire 1 % rst $end
$var reg 1 ! dout $end
$var reg 4 ' temp [3:0] $end
$upscope $end
$upscope $end
$enddefinitions $end
$comment Show the parameter values. $end
$dumpall
$end
#0
$dumpvars
b0 '
bx &
1%
x$
bx #
0"
0!
$end
#5
1"
#10
0"
1$
b1101 #
b1101 &
0%
#15
b1101 '
1"
#20
0"
0$
#25
1!
b1010 '
1"
#30
0"
#35
b100 '
1"
#40
0"
#45
0!
b1000 '
1"
#50
0"
#55
b0 '
1!
1"
