verilog/day06_counter_and _registers/sipo.v
module sipo(
input clk,
input rst,
input sin,
output reg[3:0] q
);
always @(posedge clk or posedge rst) begin
	if (rst)
		q <= 0;
	else
		q <={q[2:0],sin};

end
endmodule

verilog/day06_counter_and _registers/sipo_tb.v
module sipo_tb;
  reg clk, rst, sin;
  wire [3:0] q;

  sipo uut (.clk(clk), .rst(rst), .sin(sin), .q(q));

  initial begin
    $dumpfile("sipo.vcd");
    $dumpvars(0, sipo_tb);
    clk = 0;
    forever #5 clk = ~clk;
  end

  initial begin
    rst = 1; #10;
    rst = 0;
    sin = 1; #10;
    sin = 0; #10;
    sin = 1; #10;
    sin = 1; #10;
    $finish;
  end
endmodule

verilog/day06_counter_and _registers/sipo.vcd
$date
	Fri May 30 20:15:04 2025
$end
$version
	Icarus Verilog
$end
$timescale
	1s
$end
$scope module sipo_tb $end
$var wire 4 ! q [3:0] $end
$var reg 1 " clk $end
$var reg 1 # rst $end
$var reg 1 $ sin $end
$scope module uut $end
$var wire 1 " clk $end
$var wire 1 # rst $end
$var wire 1 $ sin $end
$var reg 4 % q [3:0] $end
$upscope $end
$upscope $end
$enddefinitions $end
$comment Show the parameter values. $end
$dumpall
$end
#0
$dumpvars
b0 %
x$
1#
0"
b0 !
$end
#5
1"
#10
0"
1$
0#
#15
b1 !
b1 %
1"
#20
0"
0$
#25
b10 !
b10 %
1"
#30
0"
1$
#35
b101 !
b101 %
1"
#40
0"
#45
b1011 !
b1011 %
1"
