systemverilog/day05_flip_flop/jk_ff.sv
module jk_ff (
  input logic clk,
  input logic j, k,
  output logic q
);
  always_ff @(posedge clk)
    case ({j, k})
      2'b00: q <= q;
      2'b01: q <= 0;
      2'b10: q <= 1;
      2'b11: q <= ~q;
    endcase
endmodule

systemverilog/day05_flip_flop/jk_ff_tb.sv
module jk_ff_tb;
  logic clk, j, k, q;

  jk_ff uut (.clk(clk), .j(j), .k(k), .q(q));

  initial begin
    $dumpfile("jk_ff.vcd");
    $dumpvars(0, jk_ff_tb);

    clk = 0;
    forever #5 clk = ~clk;
  end

  initial begin
    j = 0; k = 0; #10;
    j = 1; k = 0; #10;
    j = 0; k = 1; #10;
    j = 1; k = 1; #10;
    j = 0; k = 0; #10;
    $finish;
  end
endmodule

systemverilog/day05_flip_flop/jk_ff.vcd
$date
	Thu May 29 13:15:36 2025
$end
$version
	Icarus Verilog
$end
$timescale
	1s
$end
$scope module jk_ff_tb $end
$var wire 1 ! q $end
$var reg 1 " clk $end
$var reg 1 # j $end
$var reg 1 $ k $end
$scope module uut $end
$var wire 1 " clk $end
$var wire 1 # j $end
$var wire 1 $ k $end
$var reg 1 ! q $end
$upscope $end
$upscope $end
$enddefinitions $end
$comment Show the parameter values. $end
$dumpall
$end
#0
$dumpvars
0$
0#
0"
x!
$end
#5
1"
#10
0"
1#
#15
1!
1"
#20
0"
1$
0#
#25
0!
1"
#30
0"
1#
#35
1!
1"
#40
0"
0$
0#
