verilog/day10_alu/alu_4bit.v
module alu_4bit (
  input [3:0] a, b,
  input [2:0] sel,
  output reg [3:0] out,
  output reg carry
);
  always @(*) begin
    case (sel)
      3'b000: {carry, out} = a + b;       // Addition
      3'b001: {carry, out} = a - b;       // Subtraction
      3'b010: out = a & b;                // AND
      3'b011: out = a | b;                // OR
      3'b100: out = a ^ b;                // XOR
      3'b101: out = ~a;                   // NOT A
      3'b110: out = a << 1;               // Shift Left
      3'b111: out = a >> 1;               // Shift Right
      default: out = 4'b0000;
    endcase
  end
endmodule

verilog/day10_alu/alu_4bit_tb.v
module alu_4bit_tb;
  reg [3:0] a, b;
  reg [2:0] sel;
  wire [3:0] out;
  wire carry;

  alu_4bit uut (.a(a), .b(b), .sel(sel), .out(out), .carry(carry));

  initial begin
    $dumpfile("alu_4bit.vcd");
    $dumpvars(0, alu_4bit_tb);

    a = 4'b0101; b = 4'b0011;

    sel = 3'b000; #10;  // Add
    sel = 3'b001; #10;  // Sub
    sel = 3'b010; #10;  // AND
    sel = 3'b011; #10;  // OR
    sel = 3'b100; #10;  // XOR
    sel = 3'b101; #10;  // NOT A
    sel = 3'b110; #10;  // Shift Left
    sel = 3'b111; #10;  // Shift Right

    $finish;
  end
endmodule

verilog/day10_alu/alu_4bit.vcd
$date
	Fri Jun 13 00:42:05 2025
$end
$version
	Icarus Verilog
$end
$timescale
	1s
$end
$scope module alu_4bit_tb $end
$var wire 4 ! out [3:0] $end
$var wire 1 " carry $end
$var reg 4 # a [3:0] $end
$var reg 4 $ b [3:0] $end
$var reg 3 % sel [2:0] $end
$scope module uut $end
$var wire 4 & a [3:0] $end
$var wire 4 ' b [3:0] $end
$var wire 3 ( sel [2:0] $end
$var reg 1 " carry $end
$var reg 4 ) out [3:0] $end
$upscope $end
$upscope $end
$enddefinitions $end
$comment Show the parameter values. $end
$dumpall
$end
#0
$dumpvars
b1000 )
b0 (
b11 '
b101 &
b0 %
b11 $
b101 #
0"
b1000 !
$end
#10
b10 !
b10 )
b1 %
b1 (
#20
b1 !
b1 )
b10 %
b10 (
#30
b111 !
b111 )
b11 %
b11 (
#40
b110 !
b110 )
b100 %
b100 (
#50
b1010 !
b1010 )
b101 %
b101 (
#60
b110 %
b110 (
#70
b10 !
b10 )
b111 %
b111 (
