verilog/day10_alu/alu_8bit.v
module alu_8bit(
	input[7:0] a,b,
	input [2:0] sel,
	output reg [7:0] out,
	output reg carry
);

	always @(*) begin
		case (sel)
			3'b000: {carry, out} = a + b;
			3'b001: {carry, out} = a - b;
			3'b010: out = a & b;
			3'b011: out = a | b;
			3'b100: out = a ^ b;
			3'b101: out = ~a;
			3'b110: out = a << 1;
			3'b111: out = a >> 1;
			default: out = 8'b000000000;

endcase
end 
endmodule

verilog/day10_alu/alu_8bit_tb.v
module alu_8bit_tb;
  reg [7:0] a, b;
  reg [2:0] sel;
  wire [7:0] out;
  wire carry;

  alu_8bit uut (.a(a), .b(b), .sel(sel), .out(out), .carry(carry));

  initial begin
    $dumpfile("alu_8bit.vcd");
    $dumpvars(0, alu_8bit_tb);

    a = 8'b00001100; b = 8'b00000101;

    sel = 3'b000; #10;
    sel = 3'b001; #10;
    sel = 3'b010; #10;
    sel = 3'b011; #10;
    sel = 3'b100; #10;
    sel = 3'b101; #10;
    sel = 3'b110; #10;
    sel = 3'b111; #10;

    $finish;
  end
endmodule

verilog/day10_alu/alu_8bit.vcd
$date
	Fri Jun 13 00:42:21 2025
$end
$version
	Icarus Verilog
$end
$timescale
	1s
$end
$scope module alu_8bit_tb $end
$var wire 8 ! out [7:0] $end
$var wire 1 " carry $end
$var reg 8 # a [7:0] $end
$var reg 8 $ b [7:0] $end
$var reg 3 % sel [2:0] $end
$scope module uut $end
$var wire 8 & a [7:0] $end
$var wire 8 ' b [7:0] $end
$var wire 3 ( sel [2:0] $end
$var reg 1 " carry $end
$var reg 8 ) out [7:0] $end
$upscope $end
$upscope $end
$enddefinitions $end
$comment Show the parameter values. $end
$dumpall
$end
#0
$dumpvars
b10001 )
b0 (
b101 '
b1100 &
b0 %
b101 $
b1100 #
0"
b10001 !
$end
#10
b111 !
b111 )
b1 %
b1 (
#20
b100 !
b100 )
b10 %
b10 (
#30
b1101 !
b1101 )
b11 %
b11 (
#40
b1001 !
b1001 )
b100 %
b100 (
#50
b11110011 !
b11110011 )
b101 %
b101 (
#60
b11000 !
b11000 )
b110 %
b110 (
#70
b110 !
b110 )
b111 %
b111 (
