verilog/day07_fsm/moore_fsm.v
module moore_fsm (
  input clk, rst, x,
  output reg z
);
  reg [1:0] state, next_state;
  parameter S0 = 2'd0, S1 = 2'd1, S2 = 2'd2, S3 = 2'd3;

  always @(posedge clk or posedge rst)
    if (rst) state <= S0;
    else state <= next_state;

  always @(*) begin
    case (state)
      S0: next_state = x ? S1 : S0;
      S1: next_state = x ? S1 : S2;
      S2: next_state = x ? S3 : S0;
      S3: next_state = x ? S1 : S2;
      default: next_state = S0;
    endcase
  end

  always @(*) begin
    z = (state == S3);
  end
endmodule

verilog/day07_fsm/moore_fsm_tb.v
module moore_fsm_tb;
  reg clk, rst, x;
  wire z;

  moore_fsm uut (.clk(clk), .rst(rst), .x(x), .z(z));

  initial begin
    $dumpfile("moore_fsm.vcd");
    $dumpvars(0, moore_fsm_tb);
    clk = 0; forever #5 clk = ~clk;
  end

  initial begin
    rst = 1; #10; rst = 0;
    x = 1; #10;
    x = 0; #10;
    x = 1; #10; // detect 101 → z = 1 (state S3)
    x = 1; #10;
    $finish;
  end
endmodule

verilog/day07_fsm/moore_fsm.vcd
$date
	Mon Jun  2 00:54:09 2025
$end
$version
	Icarus Verilog
$end
$timescale
	1s
$end
$scope module moore_fsm_tb $end
$var wire 1 ! z $end
$var reg 1 " clk $end
$var reg 1 # rst $end
$var reg 1 $ x $end
$scope module uut $end
$var wire 1 " clk $end
$var wire 1 # rst $end
$var wire 1 $ x $end
$var parameter 2 % S0 $end
$var parameter 2 & S1 $end
$var parameter 2 ' S2 $end
$var parameter 2 ( S3 $end
$var reg 2 ) next_state [1:0] $end
$var reg 2 * state [1:0] $end
$var reg 1 ! z $end
$upscope $end
$upscope $end
$enddefinitions $end
$comment Show the parameter values. $end
$dumpall
b11 (
b10 '
b1 &
b0 %
$end
#0
$dumpvars
b0 *
b0x )
x$
1#
0"
0!
$end
#5
1"
#10
b1 )
0"
1$
0#
#15
b1 *
1"
#20
b10 )
0"
0$
#25
b0 )
b10 *
1"
#30
b11 )
0"
1$
#35
1!
b1 )
b11 *
1"
#40
0"
#45
0!
b1 *
1"
