verilog/day05_flip_flop/d_ff.v
module d_ff(
	input clk,
	input d,
	output reg q
);

always @(posedge clk) begin
	 q <= d;
end
endmodule

verilog/day05_flip_flop/d_ff_tb.v
module d_ff_tb;
  reg clk, d;
  wire q;

  d_ff uut (.clk(clk), .d(d), .q(q));

  initial begin
    $dumpfile("d_ff.vcd");
    $dumpvars(0, d_ff_tb);

    clk = 0;
    forever #5 clk = ~clk;
  end

  initial begin
    d = 0; #12;
    d = 1; #10;
    d = 0; #10;
    d = 1; #10;
    #10 $finish;
  end
endmodule

verilog/day05_flip_flop/d_ff.vcd
$date
	Thu May 29 17:22:37 2025
$end
$version
	Icarus Verilog
$end
$timescale
	1s
$end
$scope module d_ff_tb $end
$var wire 1 ! q $end
$var reg 1 " clk $end
$var reg 1 # d $end
$scope module uut $end
$var wire 1 " clk $end
$var wire 1 # d $end
$var reg 1 ! q $end
$upscope $end
$upscope $end
$enddefinitions $end
$comment Show the parameter values. $end
$dumpall
$end
#0
$dumpvars
0#
0"
x!
$end
#5
0!
1"
#10
0"
#12
1#
#15
1!
1"
#20
0"
#22
0#
#25
0!
1"
#30
0"
#32
1#
#35
1!
1"
